Workbook

Sheet Cover
A1: Nike Inc (NYSE: NKE): DCF model
A2: DCF Lab, by Rishit Jain. Educational use, not investment advice.
A4: Implied value per share | B4: =DCF!$C$32
A5: Share price at publish | B5: =Inputs!$B$18
A6: Price vs implied value | B6: =B5/B4-1
A8: How the workbook is built
A9: Inputs: every assumption in one place, with its source. Change a blue cell and the whole model updates.
A10: Historicals: reported revenue and the growth rate behind the forecast.
A11: DCF: 5-year forecast from revenue down to unlevered free cash flow, discounted at WACC, plus a Gordon growth terminal value, then the bridge from enterprise value to value per share.
A12: Sensitivity: implied value per share across a range of WACC and terminal growth rates.
A14: Colour key
A15: Blue text: hardcoded input you can change
A16: Black text: formula
A17: Green text: linked from another sheet
A18: Yellow fill: key assumption or headline result
A20: Sources
A21: Revenue FY21-FY25, EBITDA margin, D&A, capex and tax rate: Nike FY2025 Form 10-K (fiscal year ended May 31, 2025), SEC EDGAR.
... A23: Growth path, WACC and terminal growth: this model's own estimates.

Sheet Inputs
A1: Nike Inc DCF: inputs
A2: All money in $ millions; shares in millions. Blue cells are inputs you can change.
A4: Base year revenue | B4: =Historicals!C8 | C4: FY25 revenue, linked from the Historicals sheet.
A5: Assumption | B5: Value | C5: Source / note
A6: Revenue growth, year 1 | B6: 0.03 | C6: Model estimate. Held flat at 3% a year: no turnaround assumed.
A7: Revenue growth, final year | B7: 0.03 | C7: Model estimate. Held flat at 3% a year: no turnaround assumed.
A8: EBITDA margin, year 1 | B8: 0.097 | C8: FY25 EBITDA margin from the 10-K: operating income $3.7B plus $775M D&A, over $46.3B revenue.
A9: EBITDA margin, final year | B9: 0.097 | C9: FY25 EBITDA margin from the 10-K: operating income $3.7B plus $775M D&A, over $46.3B revenue.
A10: D&A, % of revenue | B10: 0.0167 | C10: FY25 D&A of $775M over revenue, Nike 10-K.
A11: Capex, % of revenue | B11: 0.0093 | C11: FY25 capital expenditure over revenue, Nike 10-K.
A12: Increase in working capital, % of revenue increase | B12: 0.02 | C12: Model estimate: working capital absorbs 2% of each year's revenue increase.
A13: Tax rate | B13: 0.171 | C13: FY25 effective tax rate, Nike 10-K.
A14: WACC (discount rate) | B14: 0.08 | C14: Model estimate.
A15: Terminal growth rate | B15: 0.025 | C15: Model estimate, roughly long-run US nominal growth.
A16: Net debt (negative = net cash) | B16: 502 | C16: Total debt less cash and short-term investments, stockanalysis.com.
A17: Diluted shares | B17: 1487.6 | C17: Diluted shares, stockanalysis.com.
A18: Share price at publish | B18: 37.21 | C18: Close of Oct 19, 2026, stockanalysis.com.
A20: Forecast years | B20: =COUNT(DCF!D5:H5) | C20: Counted from the DCF sheet's year row.

Sheet Historicals
A1: Nike Inc: revenue history
A2: $ millions
A3: Fiscal year | C3: Revenue | D3: Growth vs prior year
A4: FY21 | C4: 44538
A5: FY22 | C5: 46710 | D5: =C5/C4-1
A6: FY23 | C6: 51217 | D6: =C6/C5-1
A7: FY24 | C7: 51362 | D7: =C7/C6-1
A8: FY25 | C8: 46309 | D8: =C8/C7-1
A10: 4-year revenue CAGR | D10: =(C8/C4)^(1/4)-1
A12: Source: Revenue FY21-FY25, EBITDA margin, D&A, capex and tax rate: Nike FY2025 Form 10-K (fiscal year ended May 31, 2025), SEC EDGAR.

Sheet DCF
A1: Nike Inc: discounted cash flow
A2: $ millions, except per-share figures. End-of-year discounting.
A3: Line item | C3: FY25 | D3: Year 1 | E3: Year 2 | F3: Year 3 | G3: Year 4 | H3: Year 5
A5: Year (t) | C5: 0 | D5: 1 | E5: 2 | F5: 3 | G5: 4 | H5: 5
A7: Revenue growth | D7: =Inputs!$B$6+(Inputs!$B$7-Inputs!$B$6)*(D5-1)/MAX(Inputs!$B$20-1,1) | E7: =Inputs!$B$6+(Inputs!$B$7-Inputs!$B$6)*(E5-1)/MAX(Inputs!$B$20-1,1) | F7: =Inputs!$B$6+(Inputs!$B$7-Inputs!$B$6)*(F5-1)/MAX(Inputs!$B$20-1,1) | G7: =Inputs!$B$6+(Inputs!$B$7-Inputs!$B$6)*(G5-1)/MAX(Inputs!$B$20-1,1) | H7: =Inputs!$B$6+(Inputs!$B$7-Inputs!$B$6)*(H5-1)/MAX(Inputs!$B$20-1,1)
A8: Revenue | C8: =Inputs!$B$4 | D8: =C8*(1+D7) | E8: =D8*(1+E7) | F8: =E8*(1+F7) | G8: =F8*(1+G7) | H8: =G8*(1+H7)
A9: EBITDA margin | D9: =Inputs!$B$8+(Inputs!$B$9-Inputs!$B$8)*(D5-1)/MAX(Inputs!$B$20-1,1) | E9: =Inputs!$B$8+(Inputs!$B$9-Inputs!$B$8)*(E5-1)/MAX(Inputs!$B$20-1,1) | F9: =Inputs!$B$8+(Inputs!$B$9-Inputs!$B$8)*(F5-1)/MAX(Inputs!$B$20-1,1) | G9: =Inputs!$B$8+(Inputs!$B$9-Inputs!$B$8)*(G5-1)/MAX(Inputs!$B$20-1,1) | H9: =Inputs!$B$8+(Inputs!$B$9-Inputs!$B$8)*(H5-1)/MAX(Inputs!$B$20-1,1)
A10: EBITDA | D10: =D8*D9 | E10: =E8*E9 | F10: =F8*F9 | G10: =G8*G9 | H10: =H8*H9
A11: Less D&A | D11: =-D8*Inputs!$B$10 | E11: =-E8*Inputs!$B$10 | F11: =-F8*Inputs!$B$10 | G11: =-G8*Inputs!$B$10 | H11: =-H8*Inputs!$B$10
A12: EBIT | D12: =D10+D11 | E12: =E10+E11 | F12: =F10+F11 | G12: =G10+G11 | H12: =H10+H11
A13: Less tax on EBIT | D13: =-D12*Inputs!$B$13 | E13: =-E12*Inputs!$B$13 | F13: =-F12*Inputs!$B$13 | G13: =-G12*Inputs!$B$13 | H13: =-H12*Inputs!$B$13
A14: NOPAT | D14: =D12+D13 | E14: =E12+E13 | F14: =F12+F13 | G14: =G12+G13 | H14: =H12+H13
A15: Plus D&A | D15: =-D11 | E15: =-E11 | F15: =-F11 | G15: =-G11 | H15: =-H11
A16: Less capex | D16: =-D8*Inputs!$B$11 | E16: =-E8*Inputs!$B$11 | F16: =-F8*Inputs!$B$11 | G16: =-G8*Inputs!$B$11 | H16: =-H8*Inputs!$B$11
A17: Less increase in working capital | D17: =-(D8-C8)*Inputs!$B$12 | E17: =-(E8-D8)*Inputs!$B$12 | F17: =-(F8-E8)*Inputs!$B$12 | G17: =-(G8-F8)*Inputs!$B$12 | H17: =-(H8-G8)*Inputs!$B$12
A18: Unlevered free cash flow | D18: =D14+D15+D16+D17 | E18: =E14+E15+E16+E17 | F18: =F14+F15+F16+F17 | G18: =G14+G15+G16+G17 | H18: =H14+H15+H16+H17
A20: Discount factor = 1 / (1 + WACC)^t | D20: =1/(1+Inputs!$B$14)^D5 | E20: =1/(1+Inputs!$B$14)^E5 | F20: =1/(1+Inputs!$B$14)^F5 | G20: =1/(1+Inputs!$B$14)^G5 | H20: =1/(1+Inputs!$B$14)^H5
A21: Present value of UFCF | D21: =D18*D20 | E21: =E18*E20 | F21: =F18*F20 | G21: =G18*G20 | H21: =H18*H20
A23: Valuation | C23: Value
A24: Sum of PV of UFCF | C24: =SUM(D21:H21)
A25: Final-year UFCF | C25: =H18
A26: Terminal value = UFCF x (1 + g) / (WACC - g) | C26: =C25*(1+Inputs!$B$15)/(Inputs!$B$14-Inputs!$B$15)
A27: PV of terminal value | C27: =C26*H20
A28: Enterprise value | C28: =C24+C27
A29: Less net debt (plus net cash) | C29: =-Inputs!$B$16
A30: Equity value | C30: =C28+C29
A31: Diluted shares (millions) | C31: =Inputs!$B$17
A32: Implied value per share | C32: =C30/C31
A33: Share price at publish | C33: =Inputs!$B$18
A34: Price vs implied value | C34: =C33/C32-1
A35: Terminal value share of EV | C35: =C27/C28
A37: Check: implied value published on DCF Lab | C37: 43.18
A38: Difference (rounding only) | C38: =C32-C37

Sheet Sensitivity
A1: Nike Inc: implied value per share
A2: Rows: WACC. Columns: terminal growth. Centre cell is the base case.
A4: WACC \ g | B4: =Inputs!$B$15+(-0.01) | C4: =Inputs!$B$15+(-0.005) | D4: =Inputs!$B$15+(0) | E4: =Inputs!$B$15+(0.005) | F4: =Inputs!$B$15+(0.01)
A5: =Inputs!$B$14+(-0.02) | B5: =(SUMPRODUCT(DCF!$D$18:$H$18/(1+$A5)^DCF!$D$5:$H$5)+DCF!$H$18*(1+B$4)/($A5-B$4)/(1+$A5)^Inputs!$B$20-Inputs!$B$16)/Inputs!$B$17 | C5: =(SUMPRODUCT(DCF!$D$18:$H$18/(1+$A5)^DCF!$D$5:$H$5)+DCF!$H$18*(1+C$4)/($A5-C$4)/(1+$A5)^Inputs!$B$20-Inputs!$B$16)/Inputs!$B$17 | D5: =(SUMPRODUCT(DCF!$D$18:$H$18/(1+$A5)^DCF!$D$5:$H$5)+DCF!$H$18*(1+D$4)/($A5-D$4)/(1+$A5)^Inputs!$B$20-Inputs!$B$16)/Inputs!$B$17 | E5: =(SUMPRODUCT(DCF!$D$18:$H$18/(1+$A5)^DCF!$D$5:$H$5)+DCF!$H$18*(1+E$4)/($A5-E$4)/(1+$A5)^Inputs!$B$20-Inputs!$B$16)/Inputs!$B$17 | F5: =(SUMPRODUCT(DCF!$D$18:$H$18/(1+$A5)^DCF!$D$5:$H$5)+DCF!$H$18*(1+F$4)/($A5-F$4)/(1+$A5)^Inputs!$B$20-Inputs!$B$16)/Inputs!$B$17
A6: =Inputs!$B$14+(-0.01) | B6: =(SUMPRODUCT(DCF!$D$18:$H$18/(1+$A6)^DCF!$D$5:$H$5)+DCF!$H$18*(1+B$4)/($A6-B$4)/(1+$A6)^Inputs!$B$20-Inputs!$B$16)/Inputs!$B$17 | C6: =(SUMPRODUCT(DCF!$D$18:$H$18/(1+$A6)^DCF!$D$5:$H$5)+DCF!$H$18*(1+C$4)/($A6-C$4)/(1+$A6)^Inputs!$B$20-Inputs!$B$16)/Inputs!$B$17 | D6: =(SUMPRODUCT(DCF!$D$18:$H$18/(1+$A6)^DCF!$D$5:$H$5)+DCF!$H$18*(1+D$4)/($A6-D$4)/(1+$A6)^Inputs!$B$20-Inputs!$B$16)/Inputs!$B$17 | E6: =(SUMPRODUCT(DCF!$D$18:$H$18/(1+$A6)^DCF!$D$5:$H$5)+DCF!$H$18*(1+E$4)/($A6-E$4)/(1+$A6)^Inputs!$B$20-Inputs!$B$16)/Inputs!$B$17 | F6: =(SUMPRODUCT(DCF!$D$18:$H$18/(1+$A6)^DCF!$D$5:$H$5)+DCF!$H$18*(1+F$4)/($A6-F$4)/(1+$A6)^Inputs!$B$20-Inputs!$B$16)/Inputs!$B$17
A7: =Inputs!$B$14+(0) | B7: =(SUMPRODUCT(DCF!$D$18:$H$18/(1+$A7)^DCF!$D$5:$H$5)+DCF!$H$18*(1+B$4)/($A7-B$4)/(1+$A7)^Inputs!$B$20-Inputs!$B$16)/Inputs!$B$17 | C7: =(SUMPRODUCT(DCF!$D$18:$H$18/(1+$A7)^DCF!$D$5:$H$5)+DCF!$H$18*(1+C$4)/($A7-C$4)/(1+$A7)^Inputs!$B$20-Inputs!$B$16)/Inputs!$B$17 | D7: =(SUMPRODUCT(DCF!$D$18:$H$18/(1+$A7)^DCF!$D$5:$H$5)+DCF!$H$18*(1+D$4)/($A7-D$4)/(1+$A7)^Inputs!$B$20-Inputs!$B$16)/Inputs!$B$17 | E7: =(SUMPRODUCT(DCF!$D$18:$H$18/(1+$A7)^DCF!$D$5:$H$5)+DCF!$H$18*(1+E$4)/($A7-E$4)/(1+$A7)^Inputs!$B$20-Inputs!$B$16)/Inputs!$B$17 | F7: =(SUMPRODUCT(DCF!$D$18:$H$18/(1+$A7)^DCF!$D$5:$H$5)+DCF!$H$18*(1+F$4)/($A7-F$4)/(1+$A7)^Inputs!$B$20-Inputs!$B$16)/Inputs!$B$17
A8: =Inputs!$B$14+(0.01) | B8: =(SUMPRODUCT(DCF!$D$18:$H$18/(1+$A8)^DCF!$D$5:$H$5)+DCF!$H$18*(1+B$4)/($A8-B$4)/(1+$A8)^Inputs!$B$20-Inputs!$B$16)/Inputs!$B$17 | C8: =(SUMPRODUCT(DCF!$D$18:$H$18/(1+$A8)^DCF!$D$5:$H$5)+DCF!$H$18*(1+C$4)/($A8-C$4)/(1+$A8)^Inputs!$B$20-Inputs!$B$16)/Inputs!$B$17 | D8: =(SUMPRODUCT(DCF!$D$18:$H$18/(1+$A8)^DCF!$D$5:$H$5)+DCF!$H$18*(1+D$4)/($A8-D$4)/(1+$A8)^Inputs!$B$20-Inputs!$B$16)/Inputs!$B$17 | E8: =(SUMPRODUCT(DCF!$D$18:$H$18/(1+$A8)^DCF!$D$5:$H$5)+DCF!$H$18*(1+E$4)/($A8-E$4)/(1+$A8)^Inputs!$B$20-Inputs!$B$16)/Inputs!$B$17 | F8: =(SUMPRODUCT(DCF!$D$18:$H$18/(1+$A8)^DCF!$D$5:$H$5)+DCF!$H$18*(1+F$4)/($A8-F$4)/(1+$A8)^Inputs!$B$20-Inputs!$B$16)/Inputs!$B$17
A9: =Inputs!$B$14+(0.02) | B9: =(SUMPRODUCT(DCF!$D$18:$H$18/(1+$A9)^DCF!$D$5:$H$5)+DCF!$H$18*(1+B$4)/($A9-B$4)/(1+$A9)^Inputs!$B$20-Inputs!$B$16)/Inputs!$B$17 | C9: =(SUMPRODUCT(DCF!$D$18:$H$18/(1+$A9)^DCF!$D$5:$H$5)+DCF!$H$18*(1+C$4)/($A9-C$4)/(1+$A9)^Inputs!$B$20-Inputs!$B$16)/Inputs!$B$17 | D9: =(SUMPRODUCT(DCF!$D$18:$H$18/(1+$A9)^DCF!$D$5:$H$5)+DCF!$H$18*(1+D$4)/($A9-D$4)/(1+$A9)^Inputs!$B$20-Inputs!$B$16)/Inputs!$B$17 | E9: =(SUMPRODUCT(DCF!$D$18:$H$18/(1+$A9)^DCF!$D$5:$H$5)+DCF!$H$18*(1+E$4)/($A9-E$4)/(1+$A9)^Inputs!$B$20-Inputs!$B$16)/Inputs!$B$17 | F9: =(SUMPRODUCT(DCF!$D$18:$H$18/(1+$A9)^DCF!$D$5:$H$5)+DCF!$H$18*(1+F$4)/($A9-F$4)/(1+$A9)^Inputs!$B$20-Inputs!$B$16)/Inputs!$B$17
A11: Each cell recomputes the full DCF at that WACC and terminal growth: PV of the UFCF row plus PV of the terminal value, less net debt, over diluted shares.
