Workbook

Sheet Cover
A1: Zomato Ltd (Eternal Limited) (NSE: ETERNAL): DCF model
A4: Implied value per share | B4: =DCF!$C$32 -> 105.15347
A5: Share price at publish | B5: =Inputs!$B$18 -> 322.55
A6: Price vs implied value | B6: =B5/B4-1 -> 2.0674214
A8: How the workbook is built
A9: Inputs: every assumption in one place, with its source. Change a blue cell and the whole model updates.
A10: Historicals: reported revenue and the growth rate behind the forecast.
A11: DCF: 10-year forecast from revenue down to unlevered free cash flow, discounted at WACC, plus a Gordon growth terminal value, then the bridge from enterprise value to value per share.
A12: Sensitivity: implied value per share across a range of WACC and terminal growth rates.
A14: Colour key
A15: Blue text: hardcoded input you can change
A16: Black text: formula
A17: Green text: linked from another sheet
A18: Yellow fill: key assumption or headline result
A20: Sources
A21: Revenue FY21-FY25 and D&A: Eternal Limited FY25 annual report (year ended March 31, 2025), via screener.in.
... A24: Growth and margin path, capex %, WACC and terminal growth: this model's own estimates.

Sheet Inputs
A1: Zomato Ltd (Eternal Limited) DCF: inputs
A4: Base year revenue | B4: =Historicals!C8 -> 20243 | C4: FY25 revenue
A5: Assumption | B5: Value | C5: Source
A6: Revenue growth, year 1 | B6: 0.3 | C6: Model estimate. Year 1 growth; slows in equal steps to the final-year rate.
A7: Revenue growth, final year | B7: 0.08 | C7: Model estimate. Growth in the last forecast year.
A8: EBITDA margin, year 1 | B8: 0.06 | C8: Model estimate, a little above FY25's 3-5% as the business scales.
A9: EBITDA margin, final year | B9: 0.2 | C9: Model estimate for a mature food delivery and quick commerce business.
A10: D&A, % of revenue | B10: 0.0426 | C10: FY25 D&A over revenue, FY25 annual report.
A11: Capex, % of revenue | B11: 0.046 | C11: Model estimate.
A12: Increase in working capital, % of revenue increase | B12: 0.02 | C12: Model estimate: working capital absorbs 2% of each year's revenue increase.
A13: Tax rate | B13: 0.244 | C13: Indian corporate tax rate used in the model.
A14: WACC (discount rate) | B14: 0.12 | C14: Equals the cost of equity from the CAPM check below; Eternal has almost no debt.
A15: Terminal growth rate | B15: 0.05 | C15: Model estimate, roughly long-run Indian nominal GDP growth.
A16: Net debt (negative = net cash) | B16: -16779 | C16: Negative means net cash: ₹2,045 cr debt minus ₹18,824 cr cash balance.
A17: Diluted shares | B17: 958 | C17: FY25 net profit divided by diluted EPS.
A18: Share price at publish | B18: 322.55 | C18: Close of Oct 19, 2026, screener.in.
A20: Forecast years | B20: =COUNT(DCF!D5:M5) -> 10 | C20: Counted from the DCF sheet's year row.
A22: WACC cross-check (CAPM) | B22: Value | C22: Note
A23: Risk-free rate (10-yr G-sec) | B23: 0.065 | C23: Approximate 10-year Indian government bond yield.
A24: Beta | B24: 1.1 | C24: Model estimate.
A25: Equity risk premium | B25: 0.05 | C25: Model estimate for India.
A26: Cost of equity = Rf + Beta x ERP | B26: =B23+B24*B25 -> 0.12 | C26: Compare with the WACC input above.

Sheet Historicals
A1: Zomato Ltd (Eternal Limited): revenue history
A2: ₹ crore
A3: Fiscal year | C3: Revenue | D3: Growth vs prior year
A4: FY21 | C4: 1994
A5: FY22 | C5: 4192 | D5: =C5/C4-1 -> 1.1023069
A6: FY23 | C6: 7079 | D6: =C6/C5-1 -> 0.68869275
A7: FY24 | C7: 12114 | D7: =C7/C6-1 -> 0.71125865
A8: FY25 | C8: 20243 | D8: =C8/C7-1 -> 0.67104177
A10: 4-year revenue CAGR | D10: =(C8/C4)^(1/4)-1 -> 0.78499675

Sheet DCF
A1: Zomato Ltd (Eternal Limited): discounted cash flow
A3: Line item | C3: FY25 | D3: Year 1 | E3: Year 2 | F3: Year 3 | G3: Year 4 | H3: Year 5 | I3: Year 6 | J3: Year 7 | K3: Year 8 | L3: Year 9 | M3: Year 10
A5: Year (t) | C5: 0 | D5: 1 | E5: 2 | F5: 3 | G5: 4 | H5: 5 | I5: 6 | J5: 7 | K5: 8 | L5: 9 | M5: 10
A7: Revenue growth | D7: =Inputs!$B$6+(Inputs!$B$7-Inputs!$B$6)*(D5-1)/MAX(Inputs!$B$20-1,1) -> 0.3 | E7: =Inputs!$B$6+(Inputs!$B$7-Inputs!$B$6)*(E5-1)/MAX(Inputs!$B$20-1,1) -> 0.27555556 | F7: =Inputs!$B$6+(Inputs!$B$7-Inputs!$B$6)*(F5-1)/MAX(Inputs!$B$20-1,1) -> 0.25111111 | G7: =Inputs!$B$6+(Inputs!$B$7-Inputs!$B$6)*(G5-1)/MAX(Inputs!$B$20-1,1) -> 0.22666667 | H7: =Inputs!$B$6+(Inputs!$B$7-Inputs!$B$6)*(H5-1)/MAX(Inputs!$B$20-1,1) -> 0.20222222 | I7: =Inputs!$B$6+(Inputs!$B$7-Inputs!$B$6)*(I5-1)/MAX(Inputs!$B$20-1,1) -> 0.17777778 | J7: =Inputs!$B$6+(Inputs!$B$7-Inputs!$B$6)*(J5-1)/MAX(Inputs!$B$20-1,1) -> 0.15333333 | K7: =Inputs!$B$6+(Inputs!$B$7-Inputs!$B$6)*(K5-1)/MAX(Inputs!$B$20-1,1) -> 0.12888889 | ... M7: =Inputs!$B$6+(Inputs!$B$7-Inputs!$B$6)*(M5-1)/MAX(Inputs!$B$20-1,1) -> 0.08
A8: Revenue | C8: =Inputs!$B$4 -> 20243 | D8: =C8*(1+D7) -> 26315.9 | E8: =D8*(1+E7) -> 33567.392 | F8: =E8*(1+F7) -> 41996.538 | G8: =F8*(1+G7) -> 51515.753 | H8: =G8*(1+H7) -> 61933.383 | I8: =H8*(1+I7) -> 72943.762 | J8: =I8*(1+J7) -> 84128.472 | K8: =J8*(1+K7) -> 94971.698 | ... M8: =L8*(1+M7) -> 113282.24
A9: EBITDA margin | D9: =Inputs!$B$8+(Inputs!$B$9-Inputs!$B$8)*(D5-1)/MAX(Inputs!$B$20-1,1) -> 0.06 | E9: =Inputs!$B$8+(Inputs!$B$9-Inputs!$B$8)*(E5-1)/MAX(Inputs!$B$20-1,1) -> 0.075555556 | F9: =Inputs!$B$8+(Inputs!$B$9-Inputs!$B$8)*(F5-1)/MAX(Inputs!$B$20-1,1) -> 0.091111111 | G9: =Inputs!$B$8+(Inputs!$B$9-Inputs!$B$8)*(G5-1)/MAX(Inputs!$B$20-1,1) -> 0.10666667 | H9: =Inputs!$B$8+(Inputs!$B$9-Inputs!$B$8)*(H5-1)/MAX(Inputs!$B$20-1,1) -> 0.12222222 | I9: =Inputs!$B$8+(Inputs!$B$9-Inputs!$B$8)*(I5-1)/MAX(Inputs!$B$20-1,1) -> 0.13777778 | J9: =Inputs!$B$8+(Inputs!$B$9-Inputs!$B$8)*(J5-1)/MAX(Inputs!$B$20-1,1) -> 0.15333333 | K9: =Inputs!$B$8+(Inputs!$B$9-Inputs!$B$8)*(K5-1)/MAX(Inputs!$B$20-1,1) -> 0.16888889 | ... M9: =Inputs!$B$8+(Inputs!$B$9-Inputs!$B$8)*(M5-1)/MAX(Inputs!$B$20-1,1) -> 0.2
A10: EBITDA | D10: =D8*D9 -> 1578.954 | E10: =E8*E9 -> 2536.203 | F10: =F8*F9 -> 3826.3512 | G10: =G8*G9 -> 5495.0136 | H10: =H8*H9 -> 7569.6357 | I10: =I8*I9 -> 10050.029 | J10: =J8*J9 -> 12899.699 | K10: =K8*K9 -> 16039.664 | ... M10: =M8*M9 -> 22656.448
A11: Less D&A | D11: =-D8*Inputs!$B$10 -> -1121.0573 | E11: =-E8*Inputs!$B$10 -> -1429.9709 | F11: =-F8*Inputs!$B$10 -> -1789.0525 | G11: =-G8*Inputs!$B$10 -> -2194.5711 | H11: =-H8*Inputs!$B$10 -> -2638.3621 | I11: =-I8*Inputs!$B$10 -> -3107.4043 | J11: =-J8*Inputs!$B$10 -> -3583.8729 | K11: =-K8*Inputs!$B$10 -> -4045.7943 | ... M11: =-M8*Inputs!$B$10 -> -4825.8235
A12: EBIT | D12: =D10+D11 -> 457.89666 | E12: =E10+E11 -> 1106.2321 | F12: =F10+F11 -> 2037.2987 | G12: =G10+G11 -> 3300.4426 | H12: =H10+H11 -> 4931.2736 | I12: =I10+I11 -> 6942.6252 | J12: =J10+J11 -> 9315.8262 | K12: =K10+K11 -> 11993.87 | ... M12: =M10+M11 -> 17830.625
A13: Less tax on EBIT | D13: =-D12*Inputs!$B$13 -> -111.72679 | E13: =-E12*Inputs!$B$13 -> -269.92062 | F13: =-F12*Inputs!$B$13 -> -497.10088 | G13: =-G12*Inputs!$B$13 -> -805.30799 | H13: =-H12*Inputs!$B$13 -> -1203.2308 | I13: =-I12*Inputs!$B$13 -> -1694.0005 | J13: =-J12*Inputs!$B$13 -> -2273.0616 | K13: =-K12*Inputs!$B$13 -> -2926.5043 | ... M13: =-M12*Inputs!$B$13 -> -4350.6724
A14: NOPAT | D14: =D12+D13 -> 346.16987 | E14: =E12+E13 -> 836.31144 | F14: =F12+F13 -> 1540.1978 | G14: =G12+G13 -> 2495.1346 | H14: =H12+H13 -> 3728.0428 | I14: =I12+I13 -> 5248.6246 | J14: =J12+J13 -> 7042.7646 | K14: =K12+K13 -> 9067.3658 | ... M14: =M12+M13 -> 13479.952
A15: Plus D&A | D15: =-D11 -> 1121.0573 | E15: =-E11 -> 1429.9709 | F15: =-F11 -> 1789.0525 | G15: =-G11 -> 2194.5711 | H15: =-H11 -> 2638.3621 | I15: =-I11 -> 3107.4043 | J15: =-J11 -> 3583.8729 | K15: =-K11 -> 4045.7943 | ... M15: =-M11 -> 4825.8235
A16: Less capex | D16: =-D8*Inputs!$B$11 -> -1210.5314 | E16: =-E8*Inputs!$B$11 -> -1544.1001 | F16: =-F8*Inputs!$B$11 -> -1931.8407 | G16: =-G8*Inputs!$B$11 -> -2369.7246 | H16: =-H8*Inputs!$B$11 -> -2848.9356 | I16: =-I8*Inputs!$B$11 -> -3355.4131 | J16: =-J8*Inputs!$B$11 -> -3869.9097 | K16: =-K8*Inputs!$B$11 -> -4368.6981 | ... M16: =-M8*Inputs!$B$11 -> -5210.9831
A17: Less increase in working capital | D17: =-(D8-C8)*Inputs!$B$12 -> -121.458 | E17: =-(E8-D8)*Inputs!$B$12 -> -145.02985 | F17: =-(F8-E8)*Inputs!$B$12 -> -168.5829 | G17: =-(G8-F8)*Inputs!$B$12 -> -190.3843 | H17: =-(H8-G8)*Inputs!$B$12 -> -208.3526 | I17: =-(I8-H8)*Inputs!$B$12 -> -220.20758 | J17: =-(J8-I8)*Inputs!$B$12 -> -223.6942 | K17: =-(K8-J8)*Inputs!$B$12 -> -216.86451 | ... M17: =-(M8-L8)*Inputs!$B$12 -> -167.82554
A18: Unlevered free cash flow | D18: =D14+D15+D16+D17 -> 135.23781 | E18: =E14+E15+E16+E17 -> 577.15246 | F18: =F14+F15+F16+F17 -> 1228.8267 | G18: =G14+G15+G16+G17 -> 2129.5967 | H18: =H14+H15+H16+H17 -> 3309.1167 | I18: =I14+I15+I16+I17 -> 4780.4083 | J18: =J14+J15+J16+J17 -> 6533.0336 | K18: =K14+K15+K16+K17 -> 8527.5976 | ... M18: =M14+M15+M16+M17 -> 12926.967
A20: Discount factor = 1 / (1 + WACC)^t | D20: =1/(1+Inputs!$B$14)^D5 -> 0.89285714 | E20: =1/(1+Inputs!$B$14)^E5 -> 0.79719388 | F20: =1/(1+Inputs!$B$14)^F5 -> 0.71178025 | G20: =1/(1+Inputs!$B$14)^G5 -> 0.63551808 | H20: =1/(1+Inputs!$B$14)^H5 -> 0.56742686 | I20: =1/(1+Inputs!$B$14)^I5 -> 0.50663112 | J20: =1/(1+Inputs!$B$14)^J5 -> 0.45234922 | K20: =1/(1+Inputs!$B$14)^K5 -> 0.40388323 | ... M20: =1/(1+Inputs!$B$14)^M5 -> 0.32197324
A21: Present value of UFCF | D21: =D18*D20 -> 120.74805 | E21: =E18*E20 -> 460.10241 | F21: =F18*F20 -> 874.65456 | G21: =G18*G20 -> 1353.3972 | H21: =H18*H20 -> 1877.6817 | I21: =I18*I20 -> 2421.9036 | J21: =J18*J20 -> 2955.2126 | K21: =K18*K20 -> 3444.1536 | ... M21: =M18*M20 -> 4162.1374
A23: Valuation | C23: Value
A24: Sum of PV of UFCF | C24: =SUM(D21:M21) -> 21525.96
A25: Final-year UFCF | C25: =M18 -> 12926.967
A26: Terminal value = UFCF x (1 + g) / (WACC - g) | C26: =C25*(1+Inputs!$B$15)/(Inputs!$B$14-Inputs!$B$15) -> 193904.51
A27: PV of terminal value | C27: =C26*M20 -> 62432.062
A28: Enterprise value | C28: =C24+C27 -> 83958.022
A29: Less net debt (plus net cash) | C29: =-Inputs!$B$16 -> 16779
A30: Equity value | C30: =C28+C29 -> 100737.02
A31: Diluted shares (crore) | C31: =Inputs!$B$17 -> 958
A32: Implied value per share | C32: =C30/C31 -> 105.15347
A33: Share price at publish | C33: =Inputs!$B$18 -> 322.55
A34: Price vs implied value | C34: =C33/C32-1 -> 2.0674214
A35: Terminal value share of EV | C35: =C27/C28 -> 0.74361044
A37: Check: implied value published on DCF Lab | C37: 105.15
A38: Difference (rounding only) | C38: =C32-C37 -> 0.0034671956

Sheet Sensitivity
A1: Zomato Ltd (Eternal Limited): implied value per share
A4: WACC \ g | B4: =Inputs!$B$15+(-0.01) -> 0.04 | C4: =Inputs!$B$15+(-0.005) -> 0.045 | D4: =Inputs!$B$15+(0) -> 0.05 | E4: =Inputs!$B$15+(0.005) -> 0.055 | F4: =Inputs!$B$15+(0.01) -> 0.06
A5: =Inputs!$B$14+(-0.02) -> 0.1 | B5: =(SUMPRODUCT(DCF!$D$18:$M$18/(1+$A5)^DCF!$D$5:$M$5)+DCF!$M$18*(1+B$4)/($A5-B$4)/(1+$A5)^Inputs!$B$20-Inputs!$B$16)/Inputs!$B$17 -> 133.34752 | C5: =(SUMPRODUCT(DCF!$D$18:$M$18/(1+$A5)^DCF!$D$5:$M$5)+DCF!$M$18*(1+C$4)/($A5-C$4)/(1+$A5)^Inputs!$B$20-Inputs!$B$16)/Inputs!$B$17 -> 142.0182 | D5: =(SUMPRODUCT(DCF!$D$18:$M$18/(1+$A5)^DCF!$D$5:$M$5)+DCF!$M$18*(1+D$4)/($A5-D$4)/(1+$A5)^Inputs!$B$20-Inputs!$B$16)/Inputs!$B$17 -> 152.42301 | E5: =(SUMPRODUCT(DCF!$D$18:$M$18/(1+$A5)^DCF!$D$5:$M$5)+DCF!$M$18*(1+E$4)/($A5-E$4)/(1+$A5)^Inputs!$B$20-Inputs!$B$16)/Inputs!$B$17 -> 165.14001 | F5: =(SUMPRODUCT(DCF!$D$18:$M$18/(1+$A5)^DCF!$D$5:$M$5)+DCF!$M$18*(1+F$4)/($A5-F$4)/(1+$A5)^Inputs!$B$20-Inputs!$B$16)/Inputs!$B$17 -> 181.03625
A6: =Inputs!$B$14+(-0.01) -> 0.11 | B6: =(SUMPRODUCT(DCF!$D$18:$M$18/(1+$A6)^DCF!$D$5:$M$5)+DCF!$M$18*(1+B$4)/($A6-B$4)/(1+$A6)^Inputs!$B$20-Inputs!$B$16)/Inputs!$B$17 -> 112.11881 | C6: =(SUMPRODUCT(DCF!$D$18:$M$18/(1+$A6)^DCF!$D$5:$M$5)+DCF!$M$18*(1+C$4)/($A6-C$4)/(1+$A6)^Inputs!$B$20-Inputs!$B$16)/Inputs!$B$17 -> 117.91554 | D6: =(SUMPRODUCT(DCF!$D$18:$M$18/(1+$A6)^DCF!$D$5:$M$5)+DCF!$M$18*(1+D$4)/($A6-D$4)/(1+$A6)^Inputs!$B$20-Inputs!$B$16)/Inputs!$B$17 -> 124.67839 | E6: =(SUMPRODUCT(DCF!$D$18:$M$18/(1+$A6)^DCF!$D$5:$M$5)+DCF!$M$18*(1+E$4)/($A6-E$4)/(1+$A6)^Inputs!$B$20-Inputs!$B$16)/Inputs!$B$17 -> 132.67085 | F6: =(SUMPRODUCT(DCF!$D$18:$M$18/(1+$A6)^DCF!$D$5:$M$5)+DCF!$M$18*(1+F$4)/($A6-F$4)/(1+$A6)^Inputs!$B$20-Inputs!$B$16)/Inputs!$B$17 -> 142.2618
A7: =Inputs!$B$14+(0) -> 0.12 | B7: =(SUMPRODUCT(DCF!$D$18:$M$18/(1+$A7)^DCF!$D$5:$M$5)+DCF!$M$18*(1+B$4)/($A7-B$4)/(1+$A7)^Inputs!$B$20-Inputs!$B$16)/Inputs!$B$17 -> 96.464245 | C7: =(SUMPRODUCT(DCF!$D$18:$M$18/(1+$A7)^DCF!$D$5:$M$5)+DCF!$M$18*(1+C$4)/($A7-C$4)/(1+$A7)^Inputs!$B$20-Inputs!$B$16)/Inputs!$B$17 -> 100.51922 | D7: =(SUMPRODUCT(DCF!$D$18:$M$18/(1+$A7)^DCF!$D$5:$M$5)+DCF!$M$18*(1+D$4)/($A7-D$4)/(1+$A7)^Inputs!$B$20-Inputs!$B$16)/Inputs!$B$17 -> 105.15347 | E7: =(SUMPRODUCT(DCF!$D$18:$M$18/(1+$A7)^DCF!$D$5:$M$5)+DCF!$M$18*(1+E$4)/($A7-E$4)/(1+$A7)^Inputs!$B$20-Inputs!$B$16)/Inputs!$B$17 -> 110.50068 | F7: =(SUMPRODUCT(DCF!$D$18:$M$18/(1+$A7)^DCF!$D$5:$M$5)+DCF!$M$18*(1+F$4)/($A7-F$4)/(1+$A7)^Inputs!$B$20-Inputs!$B$16)/Inputs!$B$17 -> 116.7391
A8: =Inputs!$B$14+(0.01) -> 0.13 | B8: =(SUMPRODUCT(DCF!$D$18:$M$18/(1+$A8)^DCF!$D$5:$M$5)+DCF!$M$18*(1+B$4)/($A8-B$4)/(1+$A8)^Inputs!$B$20-Inputs!$B$16)/Inputs!$B$17 -> 84.507335 | C8: =(SUMPRODUCT(DCF!$D$18:$M$18/(1+$A8)^DCF!$D$5:$M$5)+DCF!$M$18*(1+C$4)/($A8-C$4)/(1+$A8)^Inputs!$B$20-Inputs!$B$16)/Inputs!$B$17 -> 87.443184 | D8: =(SUMPRODUCT(DCF!$D$18:$M$18/(1+$A8)^DCF!$D$5:$M$5)+DCF!$M$18*(1+D$4)/($A8-D$4)/(1+$A8)^Inputs!$B$20-Inputs!$B$16)/Inputs!$B$17 -> 90.746014 | E8: =(SUMPRODUCT(DCF!$D$18:$M$18/(1+$A8)^DCF!$D$5:$M$5)+DCF!$M$18*(1+E$4)/($A8-E$4)/(1+$A8)^Inputs!$B$20-Inputs!$B$16)/Inputs!$B$17 -> 94.489222 | F8: =(SUMPRODUCT(DCF!$D$18:$M$18/(1+$A8)^DCF!$D$5:$M$5)+DCF!$M$18*(1+F$4)/($A8-F$4)/(1+$A8)^Inputs!$B$20-Inputs!$B$16)/Inputs!$B$17 -> 98.767173
A9: =Inputs!$B$14+(0.02) -> 0.14 | B9: =(SUMPRODUCT(DCF!$D$18:$M$18/(1+$A9)^DCF!$D$5:$M$5)+DCF!$M$18*(1+B$4)/($A9-B$4)/(1+$A9)^Inputs!$B$20-Inputs!$B$16)/Inputs!$B$17 -> 75.123654 | C9: =(SUMPRODUCT(DCF!$D$18:$M$18/(1+$A9)^DCF!$D$5:$M$5)+DCF!$M$18*(1+C$4)/($A9-C$4)/(1+$A9)^Inputs!$B$20-Inputs!$B$16)/Inputs!$B$17 -> 77.30756 | D9: =(SUMPRODUCT(DCF!$D$18:$M$18/(1+$A9)^DCF!$D$5:$M$5)+DCF!$M$18*(1+D$4)/($A9-D$4)/(1+$A9)^Inputs!$B$20-Inputs!$B$16)/Inputs!$B$17 -> 79.734122 | E9: =(SUMPRODUCT(DCF!$D$18:$M$18/(1+$A9)^DCF!$D$5:$M$5)+DCF!$M$18*(1+E$4)/($A9-E$4)/(1+$A9)^Inputs!$B$20-Inputs!$B$16)/Inputs!$B$17 -> 82.446161 | F9: =(SUMPRODUCT(DCF!$D$18:$M$18/(1+$A9)^DCF!$D$5:$M$5)+DCF!$M$18*(1+F$4)/($A9-F$4)/(1+$A9)^Inputs!$B$20-Inputs!$B$16)/Inputs!$B$17 -> 85.497206
